pymaws/__init__.py
pymaws/pymaws.py
pymaws/test_pymaws.py
pymaws-0.1.0.dist-info/LICENSE
pymaws-0.1.0.dist-info/METADATA
pymaws-0.1.0.dist-info/WHEEL
pymaws-0.1.0.dist-info/top_level.txt
pymaws-0.1.0.dist-info/RECORD
