Metadata-Version: 2.1
Name: pymaws
Version: 0.1.0
Summary: Matsuno Analytical Wave Solution implemented in Python
Home-page: https://github.com/ofershamir/matsuno
Author: Ofer Shamir
Author-email: ofer.shamir@mail.huji.ac.il
License: UNKNOWN
Platform: UNKNOWN
Classifier: Programming Language :: Python :: 3
Classifier: License :: OSI Approved :: MIT License
Classifier: Operating System :: OS Independent
